devsnets/__init__.cp38-win_amd64.pyd
devsnets/__init__.py
devsnets/__main__.cp38-win_amd64.pyd
devsnets/__main__.py
devsnets/api.cp38-win_amd64.pyd
devsnets/client.cp38-win_amd64.pyd
devsnets/exceptions.cp38-win_amd64.pyd
devsnets/__internal/__init__.cp38-win_amd64.pyd
devsnets/__internal/__init__.py
devsnets/__internal/cli.cp38-win_amd64.pyd
devsnets/__internal/decorators.cp38-win_amd64.pyd
devsnets/__internal/connectors/__init__.cp38-win_amd64.pyd
devsnets/__internal/connectors/__init__.py
devsnets/__internal/connectors/algorithm.cp38-win_amd64.pyd
devsnets/__internal/connectors/config.cp38-win_amd64.pyd
devsnets/__internal/connectors/errors.cp38-win_amd64.pyd
devsnets/__internal/connectors/exceptions.cp38-win_amd64.pyd
devsnets/__internal/connectors/machines.cp38-win_amd64.pyd
devsnets/__internal/connectors/tracking/__init__.cp38-win_amd64.pyd
devsnets/__internal/connectors/tracking/__init__.py
devsnets/__internal/connectors/tracking/settings.cp38-win_amd64.pyd
devsnets/__internal/connectors/user/__init__.cp38-win_amd64.pyd
devsnets/__internal/connectors/user/__init__.py
devsnets/__internal/connectors/user/authentication.cp38-win_amd64.pyd
devsnets/__internal/connectors/user/profile.cp38-win_amd64.pyd
devsnets/__internal/controllers/__init__.cp38-win_amd64.pyd
devsnets/__internal/controllers/__init__.py
devsnets/__internal/controllers/algorithm/__init__.cp38-win_amd64.pyd
devsnets/__internal/controllers/algorithm/__init__.py
devsnets/__internal/controllers/algorithm/operations.cp38-win_amd64.pyd
devsnets/__internal/controllers/algorithm/setup.cp38-win_amd64.pyd
devsnets/__internal/controllers/machines/__init__.cp38-win_amd64.pyd
devsnets/__internal/controllers/machines/__init__.py
devsnets/__internal/controllers/machines/operations.cp38-win_amd64.pyd
devsnets/__internal/controllers/machines/setup.cp38-win_amd64.pyd
devsnets/__internal/controllers/setup/__init__.cp38-win_amd64.pyd
devsnets/__internal/controllers/setup/__init__.py
devsnets-1.9.6.dist-info/METADATA
devsnets-1.9.6.dist-info/WHEEL
devsnets-1.9.6.dist-info/entry_points.txt
devsnets-1.9.6.dist-info/top_level.txt
devsnets-1.9.6.dist-info/RECORD
